setup.py
api_agent/__init__.py
api_agent/example.py
api_agent-0.0.1.dist-info/LICENSE
api_agent-0.0.1.dist-info/METADATA
api_agent-0.0.1.dist-info/WHEEL
api_agent-0.0.1.dist-info/top_level.txt
api_agent-0.0.1.dist-info/RECORD
