Metadata-Version: 2.1
Name: api-agent
Version: 0.0.1
Summary: API Agent. Enables copilot to use thousands of APIs
Author-email: QiangLi <qiangli@microsoft.com>
Classifier: Programming Language :: Python :: 3
Classifier: License :: OSI Approved :: MIT License
Classifier: Operating System :: OS Independent
Requires-Python: >=3.9
License-File: LICENSE
